marketplace_scrapper-0.0.1.dist-info/DESCRIPTION.rst
marketplace_scrapper-0.0.1.dist-info/METADATA
marketplace_scrapper-0.0.1.dist-info/metadata.json
marketplace_scrapper-0.0.1.dist-info/RECORD
marketplace_scrapper-0.0.1.dist-info/top_level.txt
marketplace_scrapper-0.0.1.dist-info/WHEEL
scrap/extension.py
scrap/__init__.py
vscrap/_sc.py
vscrap/_scrap.py
vscrap/__init__.py
vscrap/tests/test_scrap.py
vscrap/tests/__init__.py
