Metadata-Version: 2.0
Name: marketplace-scrapper
Version: 0.0.1
Summary: Extract details of a (visual studio, vscode, azure devops) extension from https://marketplace.visualstudio.com
Home-page: https://github.com/muremwa/VSmarketplace-scrapper
Author: Muremwa
Author-email: danmburu254@gmail.com
License: UNKNOWN
Platform: UNKNOWN
Classifier: Programming Language :: Python :: 3
Classifier: License :: OSI Approved :: MIT License
Classifier: Operating System :: OS Independent
Requires-Python: >=3.6
